rpa_automationanywhere/__init__.py
rpa_automationanywhere/Bots/__init__.py
rpa_automationanywhere/Logs/__init__.py
rpa_automationanywhere/Schedule/__init__.py
rpa_automationanywhere/Vault/Vault.py
rpa_automationanywhere/Vault/__init__.py
rpa_automationanywhere/WLM/WLM.py
rpa_automationanywhere/WLM/__init__.py
rpa_automationanywhere-1.0.3.1.dist-info/licenses/LICENSE.txt
rpa_automationanywhere-1.0.3.1.dist-info/METADATA
rpa_automationanywhere-1.0.3.1.dist-info/WHEEL
rpa_automationanywhere-1.0.3.1.dist-info/top_level.txt
rpa_automationanywhere-1.0.3.1.dist-info/RECORD
