Metadata-Version: 2.4
Name: rpa-automationanywhere
Version: 1.0.3.1
Summary: Automation Anywhere A360 API implementation
Home-page: https://github.com/21010/rpa-automationanywhere
Author: Grzegorz Zioło
Author-email: Grzegorz Ziolo <grzegorz.ziolo@gmail.com>
License-Expression: MIT
Project-URL: Homepage, https://github.com/21010/rpa-automationanywhere
Keywords: rpa,A360,Automation Anywhere
Classifier: Development Status :: 4 - Beta
Classifier: Programming Language :: Python
Requires-Python: >=3.10
License-File: LICENSE.txt
Requires-Dist: rpaframework>=26.0.0
Provides-Extra: dev
Requires-Dist: black; extra == "dev"
Requires-Dist: bumpver; extra == "dev"
Requires-Dist: isort; extra == "dev"
Requires-Dist: pip-tools; extra == "dev"
Requires-Dist: unitest; extra == "dev"
Dynamic: author
Dynamic: home-page
Dynamic: license-file
Dynamic: requires-python
